robyn_data_validation/__init__.py
robyn_data_validation/data_review.py
robyn_data_validation-0.0.5.dist-info/LICENSE
robyn_data_validation-0.0.5.dist-info/METADATA
robyn_data_validation-0.0.5.dist-info/WHEEL
robyn_data_validation-0.0.5.dist-info/top_level.txt
robyn_data_validation-0.0.5.dist-info/RECORD
