Metadata-Version: 2.1
Name: robyn-data-validation
Version: 0.0.5
Summary: Data validation module accompanying the MMM open source package Robyn (https://github.com/facebookexperimental/Robyn)
Author-email: NGA dev team from Education First <ngadevteam@ef.com>
License: MIT License        
Project-URL: Homepage, https://github.com/yanhong-zhao-ef/robyn-data-validation
Project-URL: Bug Tracker, https://github.com/yanhong-zhao-ef/robyn-data-validation/issues
Classifier: Programming Language :: Python :: 3
Classifier: License :: OSI Approved :: MIT License
Classifier: Operating System :: OS Independent
Requires-Python: >=3.7
License-File: LICENSE
Requires-Dist: pandas (==1.4.3)
Requires-Dist: numpy (==1.23.0)
Requires-Dist: matplotlib (==3.5.2)
Requires-Dist: seaborn (==0.11.2)
Requires-Dist: statsmodels (==0.13.2)
